readmeProcess/__init__.py
getfr-0.2.4.dist-info/entry_points.txt
getfr-0.2.4.dist-info/WHEEL
getfr-0.2.4.dist-info/METADATA
getfr-0.2.4.dist-info/RECORD
