Metadata-Version: 2.1
Name: getfr
Version: 0.2.4
Summary: get fossology report for a given folder id
License: MIT
Author: dineshr93gmail.com
Requires-Python: >=3.9,<4.0
Classifier: License :: OSI Approved :: MIT License
Classifier: Programming Language :: Python :: 3
Classifier: Programming Language :: Python :: 3.9
Classifier: Programming Language :: Python :: 3.10
Requires-Dist: easy-fossy (>=2.0.11,<3.0.0)
